csmodels/__init__.py
csmodels/admin.py
csmodels/models.py
csmodels/tests.py
csmodels/views.py
django_cs_models-1.0.0.dist-info/DESCRIPTION.rst
django_cs_models-1.0.0.dist-info/METADATA
django_cs_models-1.0.0.dist-info/RECORD
django_cs_models-1.0.0.dist-info/WHEEL
django_cs_models-1.0.0.dist-info/metadata.json
django_cs_models-1.0.0.dist-info/top_level.txt
